policy.py
vault.py
exem_vault-1.1.3.dist-info/METADATA
exem_vault-1.1.3.dist-info/WHEEL
exem_vault-1.1.3.dist-info/top_level.txt
exem_vault-1.1.3.dist-info/RECORD
