Metadata-Version: 2.1
Name: exem-vault
Version: 1.1.3
Summary: All secrets now at reach.
Home-page: https://gitlab.com/exem2/libraries/api/vault
Author: Félix BOULE--REIFF
Author-email: boulereiff@exem.fr
License: BSD 2-clause
Classifier: Development Status :: 3 - Alpha
Classifier: License :: OSI Approved :: BSD License
Requires-Dist: hvac
